aws_client/__init__.py
aws_client/aws_client.py
aws_client/api_gateway/__init__.py
aws_client/api_gateway/client.py
aws_client/api_gateway/deployment.py
aws_client/aws_lambda/__init__.py
aws_client/aws_lambda/client.py
aws_client/aws_lambda/deployment.py
aws_client/aws_lambda/lambda_function.py
aws_client/eb/__init__.py
aws_client/eb/client.py
aws_client/eb/deployment.py
aws_client/elasticsearch/__init__.py
aws_client/elasticsearch/client.py
aws_client/elastictranscoder/__init__.py
aws_client/elastictranscoder/client.py
aws_client/iam/__init__.py
aws_client/iam/client.py
aws_client/s3/__init__.py
aws_client/s3/client.py
aws_client/s3/s3bucket.py
aws_client/sns/__init__.py
aws_client/sns/client.py
aws_client/sqs/__init__.py
aws_client/sqs/client.py
aws_client/sqs/queue.py
aws_client-0.11.dist-info/METADATA
aws_client-0.11.dist-info/RECORD
aws_client-0.11.dist-info/WHEEL
aws_client-0.11.dist-info/top_level.txt
