Metadata-Version: 2.1
Name: aws-client
Version: 0.11
Summary: Collectrium AWS clients
Home-page: https://github.com/collectrium/col-aws-clients
Author: collectrium
Author-email: support@collectrium.com
License: UNKNOWN
Keywords: AWS,Amazon Web Services,SQS,S3,Lambda,APIGateway
Platform: UNKNOWN
Classifier: Programming Language :: Python :: 2
Classifier: Programming Language :: Python :: 2.7
Classifier: Programming Language :: Python :: 3
Classifier: Programming Language :: Python :: 3.6
Requires-Dist: boto (==2.41.0)
Requires-Dist: boto3 (==1.3.1)
Requires-Dist: GitPython (==2.0.6)
Requires-Dist: rsa (==3.4.2)
